montecarlo
test
