Metadata-Version: 2.1
Name: imparaai-montecarlo
Version: 1.1.1
Summary: Library for running a Monte Carlo tree search either traditionally or with expert policies
Home-page: https://github.com/ImparaAI/monte-carlo-tree-search
Author: ImparaAI
Author-email: author@example.com
License: MIT
Platform: UNKNOWN
Classifier: Programming Language :: Python :: 3
Classifier: License :: OSI Approved :: MIT License
Classifier: Operating System :: OS Independent
